flutter_debugger/__init__.py
flutter_debugger/config.py
flutter_debugger/ios_app_runner.py
flutter_debugger/packager.py
flutter_debugger/server.py
flutterdebugger-5.7.data/data/bins/XdeltaCLI
flutterdebugger-5.7.data/data/bins/bundle.dart.patch
flutterdebugger-5.7.data/scripts/flutterdebugger
flutterdebugger-5.7.dist-info/LICENSE
flutterdebugger-5.7.dist-info/METADATA
flutterdebugger-5.7.dist-info/WHEEL
flutterdebugger-5.7.dist-info/top_level.txt
flutterdebugger-5.7.dist-info/RECORD
